{
  "configVersion": 1,
  "index": "/index.html",
  "assetGroups": [
    {
      "name": "app",
      "installMode": "prefetch",
      "updateMode": "prefetch",
      "urls": [
        "/favicon.ico",
        "/index.html",
        "/inline.53db66c2548aa95edf49.bundle.js",
        "/main.0a8551e2cb30adf1e03b.bundle.js",
        "/polyfills.c08331153cbf9fd50ff5.bundle.js",
        "/styles.32ff8e07c0f6137abc5d.bundle.css"
      ],
      "patterns": []
    },
    {
      "name": "assets",
      "installMode": "lazy",
      "updateMode": "prefetch",
      "urls": [
        "/assets/icons/arrow_green_43.png",
        "/assets/icons/arrow_green_86.png",
        "/assets/icons/arrow_red_43.png",
        "/assets/icons/arrow_red_86.png",
        "/assets/icons/bus_blue_24.png",
        "/assets/icons/bus_blue_48.png",
        "/assets/icons/bus_gray_24.png",
        "/assets/icons/bus_gray_48.png",
        "/assets/icons/bus_green_24.png",
        "/assets/icons/bus_green_48.png",
        "/assets/icons/bus_icon_out_14.png",
        "/assets/icons/bus_icon_out_27.png",
        "/assets/icons/bus_orange_24.png",
        "/assets/icons/bus_orange_48.png",
        "/assets/icons/bus_purple_24.png",
        "/assets/icons/bus_purple_48.png",
        "/assets/icons/bus_red_24.png",
        "/assets/icons/bus_red_48.png",
        "/assets/icons/bus_shadow_24.png",
        "/assets/icons/bus_shadow_48.png",
        "/assets/icons/bus_sky_24.png",
        "/assets/icons/bus_sky_48.png",
        "/route-data/route-index.json",
        "/route-data/route1.json",
        "/route-data/route10.json",
        "/route-data/route1000.json",
        "/route-data/route11.json",
        "/route-data/route12.json",
        "/route-data/route13.json",
        "/route-data/route140.json",
        "/route-data/route141.json",
        "/route-data/route155.json",
        "/route-data/route157.json",
        "/route-data/route16.json",
        "/route-data/route162.json",
        "/route-data/route198.json",
        "/route-data/route2.json",
        "/route-data/route217.json",
        "/route-data/route222.json",
        "/route-data/route250.json",
        "/route-data/route251.json",
        "/route-data/route31.json",
        "/route-data/route34.json",
        "/route-data/route36.json",
        "/route-data/route37.json",
        "/route-data/route40.json",
        "/route-data/route5.json",
        "/route-data/route50.json",
        "/route-data/route51.json",
        "/route-data/route53.json",
        "/route-data/route54.json",
        "/route-data/route551.json",
        "/route-data/route6.json",
        "/route-data/route66.json",
        "/route-data/route7.json",
        "/route-data/route766.json",
        "/route-data/route777.json",
        "/route-data/route790.json",
        "/route-data/route8.json",
        "/route-data/route92.json",
        "/route-data/route93.json",
        "/route-data/route94.json",
        "/route-data/route96.json",
        "/route-data/route97.json",
        "/route-data/route98.json"
      ],
      "patterns": []
    }
  ],
  "dataGroups": [],
  "hashTable": {
    "/inline.53db66c2548aa95edf49.bundle.js": "ca8cf1490578c280cc9e6245325437c009405c75",
    "/assets/icons/arrow_green_43.png": "993e5917b674c15cb16a8d5e80f7a70bf3e31eca",
    "/main.0a8551e2cb30adf1e03b.bundle.js": "7dc16425b54664b21e924b3bb8be328305279e18",
    "/assets/icons/arrow_green_86.png": "980c2a435d7ca1028942d1be0416092a0c675f5d",
    "/polyfills.c08331153cbf9fd50ff5.bundle.js": "4545b976e90c5d4eb5cb9647fb6e954cf8016259",
    "/assets/icons/arrow_red_43.png": "d99ca98c6536b0418365f132db882a1c5819e5b8",
    "/styles.32ff8e07c0f6137abc5d.bundle.css": "865cd4f55ff478539eeaa66f6804052069abb4fb",
    "/assets/icons/arrow_red_86.png": "4501f7f28f7c75022f692c633e5fa7cdf2ff99ab",
    "/favicon.ico": "bc33fea0456c0a1511ec5b0210a260449509b7c8",
    "/assets/icons/bus_blue_24.png": "9993178020dc079001f7223b924d0a1355967836",
    "/index.html": "3328d01ed4ec807d7902b6e5fb9a4d75bd532721",
    "/assets/icons/bus_blue_48.png": "885019586dfa7f4c4965822e640e8682208e901e",
    "/assets/icons/bus_gray_24.png": "51ce8db36e36b9d10be1b12d50df336d5b287781",
    "/assets/icons/bus_gray_48.png": "26a5deb557cef53c6603d4b8b2951bdf9b7beb1c",
    "/assets/icons/bus_green_24.png": "b9167b5bcec8258e1380bfdae675e7d360a5d593",
    "/assets/icons/bus_green_48.png": "d4debef0ff6114d08f3ae51fbc61fe744752ad30",
    "/assets/icons/bus_icon_out_14.png": "64ec641c5883c9155e243334619fb1b6038714d6",
    "/assets/icons/bus_icon_out_27.png": "ed7a4b1e04ca5eccfc3b255c8332c26113e19e35",
    "/assets/icons/bus_orange_24.png": "44c61a0b17b5e48a4585beba9af2055f7bc6797a",
    "/assets/icons/bus_orange_48.png": "27edebe2ea4266ba4ce3208534447df5606b96a4",
    "/assets/icons/bus_purple_24.png": "e9bffb0178e5f36858d3c09944c32715f3c25a52",
    "/assets/icons/bus_purple_48.png": "f66ad84f59f97d47eeedcbe02bad86bf1c82e453",
    "/assets/icons/bus_red_24.png": "b3e73ff595418e9a8c82d3e3092fc3715f0eff62",
    "/assets/icons/bus_red_48.png": "6c05f051c39fd054dc1bf602682a2085c8c12acf",
    "/assets/icons/bus_shadow_24.png": "b0aa4fc219affe6212510e10c85fb9447f86b5e9",
    "/assets/icons/bus_shadow_48.png": "0dcd63231855b773b732984daaef225afb00b587",
    "/assets/icons/bus_sky_24.png": "19006dde90e9301110903d4c77692e63f3ce6f0d",
    "/assets/icons/bus_sky_48.png": "7d68b137a50fd6babad5c8f249857d11f316c183",
    "/route-data/route-index.json": "a3f15ff671fe68f1d1ec82e0382a872aa8422e39",
    "/route-data/route1.json": "f821dfb524f1e9ee40121a4d6b11c35caf0f5652",
    "/route-data/route10.json": "0bbd72c99e1500b3a752f3af6ab083322b95b555",
    "/route-data/route1000.json": "a791d4f92e7f88064a050da2303abe96892fd3bb",
    "/route-data/route11.json": "e069c135422f11b860a904310bfe7b5bbf06155e",
    "/route-data/route12.json": "f37012452a8c61149e9f0b2d71979811357e2429",
    "/route-data/route13.json": "0b7f0662ebb6f9eecc7972ff727deac9d2418e36",
    "/route-data/route140.json": "db9bafe72063c5d8e43313074525f4f61b870970",
    "/route-data/route141.json": "c32c6c4a8a66a8eb26bc5d50db5b5f337c0891ea",
    "/route-data/route155.json": "70a79527bf9d2c7cc52d5098a97a7677fad33a71",
    "/route-data/route157.json": "0877f2f3c5550c28921f31b09d5ceed11b12b069",
    "/route-data/route16.json": "3ff6b29bab50f57221e95aaf90e0bc811f611ffe",
    "/route-data/route162.json": "8f188ddb653cdbb87dbfc4d208c6847f59f5c645",
    "/route-data/route198.json": "b49b0ceb07beccdd7ada51a50cd9d635ababf29f",
    "/route-data/route2.json": "a2a65085e5b777c754761a9970cec38fd7eb44df",
    "/route-data/route217.json": "2b16a883c1356005e4e91e25adc28b1fd2061386",
    "/route-data/route222.json": "a425a4c7bdafe649af20a20a2b5256c12c29cc37",
    "/route-data/route250.json": "7bbddf35f3b85131be032fa35f0a8c697adb23c6",
    "/route-data/route251.json": "384c2585ca16f1137c32129784fe5b6cbb7b8e5e",
    "/route-data/route31.json": "4611793da670eaf653d50d4ad69be6efc9206c80",
    "/route-data/route34.json": "567600c2bd99c0c0075ba24318744e322d173cfe",
    "/route-data/route36.json": "2045eaccc2de2092fe96810b6b5bbc1e0ba972af",
    "/route-data/route37.json": "32175777d71f0f6beec1b3ba15f96783780319ff",
    "/route-data/route40.json": "c1e43e0232beacc609aa70e31f7d325888fd3170",
    "/route-data/route5.json": "bd7d7b76043850f0b243a62db451abb5fd6503ca",
    "/route-data/route50.json": "c7e9887f03b6fe2b19dceed9060b623d1ef1dfbe",
    "/route-data/route51.json": "fefd718083e1368778a98a59b02c6ee656fee525",
    "/route-data/route53.json": "a875abb1d14564914b4da1fb304331d604d83884",
    "/route-data/route54.json": "27048892dd0140536b236e17b4e2df21c1a2082f",
    "/route-data/route551.json": "513de376bf197ff3a676e13f7ffca191816cf426",
    "/route-data/route6.json": "09096c708c2c11be29ddc5f7ac6b35c281ede7e0",
    "/route-data/route66.json": "f3e932b7442f1a573df83e21cd41dd683c04cee0",
    "/route-data/route7.json": "f3b12ad175427e1a4e1653b6c88d77f630b2fccc",
    "/route-data/route766.json": "b2bbb10951a4e31f0535910c5eb34ac78475272d",
    "/route-data/route777.json": "d83aa02773fa55970614e422391b5eff572630d6",
    "/route-data/route790.json": "4b438c0ef700f2eaaca4cecb2c50616c79be92c1",
    "/route-data/route8.json": "abe6bac297d21adbe9f5ff9e88c5afa74fd9c466",
    "/route-data/route92.json": "7ee90beaa54fe0ff038073d1e233f994327554bc",
    "/route-data/route93.json": "219c3ee0b3728ff83ad9355f483a06f26a341695",
    "/route-data/route94.json": "e2d771b36d385d3d0a0386f73f327e00f19376ed",
    "/route-data/route96.json": "fe1b249cf9f86434ec3b9dac52e8f8a1068c26db",
    "/route-data/route97.json": "69f82a522cca397afc961d7a6c14d50ce2ca1826",
    "/route-data/route98.json": "63695f4bddb87ddaad2bd227db8508c2d4373848"
  }
}